{
	"$schema": "http://schema.management.azure.com/schemas/2015-01-01/deploymentTemplate.json#",
	"contentVersion": "1.0.0.0",
	"parameters": {
		"_artifactsLocation": {
			"type": "string",
			"metadata": {
				"description": "Base URL for script location"
			}
		},
		"apiVersionCompute": {
			"type": "string",
			"metadata": {
				"description": "API version for compute resources"
			}
		},
		"newStorageAccountRegistry": {
			"type": "string",
			"minLength": 1,
			"metadata": {
				"description": "Storage Account for Docker Registry"
			}
		},
		"newStorageAccountKey": {
			"type": "string",
			"minLength": 1,
			"metadata": {
				"description": "Storage Account Key for Docker Registry"
			}
		},
		"newStorageAccountPersistentVolume1": {
			"type": "string",
			"minLength": 1,
			"metadata": {
				"description": "Storage Account for Persistent Volumes"
			}
		},
		"newStorageAccountPV1Key": {
			"type": "string",
			"minLength": 1,
			"metadata": {
				"description": "Storage Account Key for Persistent Volumes"
			}
		},
		"openshiftBastionHostname": {
			"type": "string",
			"minLength": 1,
			"metadata": {
				"description": "OpenShift Bastion hostname"
			}
		},
		"openshiftMasterHostname": {
			"type": "string",
			"minLength": 1,
			"metadata": {
				"description": "OpenShift Master hostname"
			}
		},
		"openshiftMasterPublicIpFqdn": {
			"type": "string",
			"minLength": 1,
			"metadata": {
				"description": "OpenShift Master VM public IP fully qualified domain name"
			}
		},
		"openshiftMasterPublicIpAddress": {
			"type": "string",
			"minLength": 1,
			"metadata": {
				"description": "OpenShift Master VM public IP address"
			}
		},
		"openshiftInfraHostname": {
			"type": "string",
			"minLength": 1,
			"metadata": {
				"description": "OpenShift Infra Node hostname"
			}
		},
		"openshiftNodeHostname": {
			"type": "string",
			"minLength": 1,
			"metadata": {
				"description": "OpenShift Node hostname"
			}
		},
		"masterInstanceCount": {
			"type": "int",
			"minValue": 1,
			"metadata": {
				"description": "Number of OpenShift Master nodes"
			}
		},
		"infraInstanceCount": {
			"type": "int",
			"minValue": 1,
			"metadata": {
				"description": "Number of OpenShift Infra nodes"
			}
		},
		"nodeInstanceCount": {
			"type": "int",
			"minValue": 1,
			"metadata": {
				"description": "Number of OpenShift nodes"
			}
		},
		"adminUsername": {
			"type": "string",
			"minLength": 1,
			"metadata": {
				"description": "Administrator username on all VMs"
			}
		},
		"openshiftPassword": {
			"type": "securestring",
			"minLength": 1,
			"metadata": {
				"description": "Administrator password for OpenShift Console"
			}
		},
		"enableMetrics": {
			"type": "string",
			"minLength": 1,
			"metadata": {
				"description": "Enable OpenShift Metrics: true or false"
			}
		},
		"enableLogging": {
			"type": "string",
			"minLength": 1,
			"metadata": {
				"description": "Enable OpenShift Logging: true or false"
			}
		},
		"enableCockpit": {
			"type": "string",
			"minLength": 1,
			"metadata": {
				"description": "Enable Cockpit: true or false"
			}
		},
		"enableAzure": {
			"type": "string",
			"minLength": 1,
			"metadata": {
				"description": "Enable Azure: true or false"
			}
		},
		"aadClientId": {
			"type": "string",
			"minLength": 1,
			"metadata": {
				"description": "Azure AD Client ID"
			}
		},
		"aadClientSecret": {
			"type": "securestring",
			"minLength": 1,
			"metadata": {
				"description": "Azure AD Client Secret"
			}
		},
		"nipioDomain": {
			"type": "string",
			"metadata": {
				"description": "nip.io Subdomain for application routing"
			}
		},
		"customDomain": {
			"type": "string",
			"metadata": {
				"description": "custom Subdomain for application routing"
			}
		},
		"subDomainChosen": {
			"type": "string",
			"metadata": {
				"description": "Subdomain chosen for application routing"
			}
		},
		"sshPrivateKey": {
			"type": "securestring",
			"minLength": 1,
			"metadata": {
				"description": "SSH private key for deploying OpenShift"
			}
		}
	},
	"variables": {
		"singlequote": "'",
		"tenantId": "[subscription().tenantId]",
		"subscriptionId": "[subscription().subscriptionId]",
		"location": "[resourceGroup().location]",
		"resourceGroupName": "[resourceGroup().name]",
		"redHatTags": {
			"app": "OpenShift",
			"provider": "9d2c71fc-96ba-4b4a-93b3-14def5bc96fc"
		},
		"openshiftDeploymentScriptUrl": "[concat(parameters('_artifactsLocation'), '/scripts/deployOpenShift.sh')]",
		"openshiftDeploymentScriptFileName": "deployOpenShift.sh"
	},
	"resources": [{
		"type": "Microsoft.Compute/virtualMachines/extensions",
		"name": "[concat(parameters('openshiftBastionHostname'), '/deployOpenShift')]",
		"location": "[resourceGroup().location]",
		"apiVersion": "[parameters('apiVersionCompute')]",
		"tags": {
			"displayName": "DeployOpenShift",
				"provider": "[variables('redHatTags').provider]",
				"app": "[variables('redHatTags').app]"
		},
		"properties": {
			"publisher": "Microsoft.Azure.Extensions",
			"type": "CustomScript",
			"typeHandlerVersion": "2.0",
			"autoUpgradeMinorVersion": true,
			"settings": {
				"fileUris": [
					"[variables('openshiftDeploymentScriptUrl')]"
				]
			},
			"protectedSettings": {
				"commandToExecute": "[concat('bash ', variables('openshiftDeploymentScriptFileName'), ' \"', parameters('adminUsername'), '\" ', variables('singlequote'), parameters('openshiftPassword'), variables('singlequote'), ' \"', parameters('sshPrivateKey'), '\" \"', parameters('openshiftMasterHostname'), '\" \"', parameters('openshiftMasterPublicIpFqdn'), '\" \"', parameters('openshiftMasterPublicIpAddress'), '\" \"', parameters('openshiftInfraHostname'), '\" \"', parameters('openshiftNodeHostname'), '\" \"', parameters('nodeInstanceCount'), '\" \"', parameters('infraInstanceCount'), '\" \"', parameters('MasterInstanceCount'), '\" \"', parameters(parameters('subDomainChosen')), '\" \"', parameters('newStorageAccountRegistry'), '\" ', variables('singlequote'), parameters('newStorageAccountKey'), variables('singlequote'), ' \"', parameters('enableMetrics'), '\" \"', parameters('enableLogging'), '\" ', variables('singlequote'), variables('tenantId'), variables('singlequote'), ' ', variables('singlequote'), variables('subscriptionId'), variables('singlequote'), ' ', variables('singlequote'), parameters('aadClientId'), variables('singlequote'), ' ', variables('singlequote'), parameters('aadClientSecret'), variables('singlequote'), ' ', variables('singlequote'), variables('resourceGroupName'), variables('singlequote'), ' ', variables('singlequote'), variables('location'), variables('singlequote'), ' ', variables('singlequote'), parameters('newStorageAccountPersistentVolume1'), variables('singlequote'), ' ', variables('singlequote'), parameters('newStorageAccountPV1Key'), variables('singlequote'), ' ', variables('singlequote'), parameters('enableCockpit'), variables('singlequote'), ' ', variables('singlequote'), parameters('enableAzure'), variables('singlequote'))]"
			}
		}
	}],
	"outputs": {}
}